tfvardoc/__init__.py
tfvardoc/grammar.py
tfvardoc/parser.py
tfvardoc-0.1.0.dist-info/DESCRIPTION.rst
tfvardoc-0.1.0.dist-info/LICENSE.txt
tfvardoc-0.1.0.dist-info/METADATA
tfvardoc-0.1.0.dist-info/RECORD
tfvardoc-0.1.0.dist-info/WHEEL
tfvardoc-0.1.0.dist-info/entry_points.txt
tfvardoc-0.1.0.dist-info/metadata.json
tfvardoc-0.1.0.dist-info/top_level.txt
