Metadata-Version: 2.0
Name: tfvardoc
Version: 0.1.0
Summary: Terraform Documentation Generator/Sync
Home-page: https://github.com/mazubieta/tf-vardoc
Author: Manuel Zubieta
Author-email: mazubieta@gmail.com
License: MIT
Keywords: terraform devops documentation
Platform: UNKNOWN
Classifier: Development Status :: 3 - Alpha
Classifier: Intended Audience :: Developers
Classifier: Topic :: Software Development :: Build Tools
Classifier: License :: OSI Approved :: MIT License
Classifier: Programming Language :: Python :: 2
Classifier: Programming Language :: Python :: 2.7
Classifier: Programming Language :: Python :: 3
Classifier: Programming Language :: Python :: 3.3
Classifier: Programming Language :: Python :: 3.4
Classifier: Programming Language :: Python :: 3.5
Requires-Dist: Jinja2
Requires-Dist: Parsley
